bobsled/__init__.py
bobsled/auth.py
bobsled/base.py
bobsled/beat.py
bobsled/callbacks/__init__.py
bobsled/callbacks/github.py
bobsled/core.py
bobsled/environments/__init__.py
bobsled/environments/paramstore_environment.py
bobsled/environments/yaml_environment.py
bobsled/exceptions.py
bobsled/runners/__init__.py
bobsled/runners/ecs_run_service.py
bobsled/runners/local_run_service.py
bobsled/runners/persisters.py
bobsled/tasks/__init__.py
bobsled/tasks/yaml_tasks.py
bobsled/templates/base.html
bobsled/templates/login.html
bobsled/tests/__init__.py
bobsled/tests/environments.yml
bobsled/tests/tasks.yml
bobsled/tests/test_api.py
bobsled/tests/test_auth.py
bobsled/tests/test_beat.py
bobsled/tests/test_environment.py
bobsled/tests/test_github_callbacks.py
bobsled/tests/test_persisters.py
bobsled/tests/test_run_service.py
bobsled/tests/test_yaml_tasks.py
bobsled/tests/testconfig.yml
bobsled/tests/users.yml
bobsled/web.py
bobsled-2.0.0.dist-info/LICENSE
bobsled-2.0.0.dist-info/WHEEL
bobsled-2.0.0.dist-info/METADATA
bobsled-2.0.0.dist-info/RECORD
