Metadata-Version: 2.1
Name: bobsled
Version: 2.0.0
Summary: 
Author: James Turk
Author-email: dev@jamesturk.net
Requires-Python: >=3.7,<4.0
Classifier: Programming Language :: Python :: 3
Classifier: Programming Language :: Python :: 3.7
Requires-Dist: aiofiles (>=0.4.0,<0.5.0)
Requires-Dist: aiosqlite (>=0.10.0,<0.11.0)
Requires-Dist: argon2_cffi (>=19.1,<20.0)
Requires-Dist: asyncpg (>=0.19.0,<0.20.0)
Requires-Dist: attrs (>=19.3,<20.0)
Requires-Dist: boto3 (>=1.9,<2.0)
Requires-Dist: databases (>=0.2.5,<0.3.0)
Requires-Dist: docker (>=4.1,<5.0)
Requires-Dist: flake8 (>=3.7,<4.0)
Requires-Dist: github3.py (>=1.3,<2.0)
Requires-Dist: jinja2 (>=2.10,<3.0)
Requires-Dist: moto (>=1.3,<2.0)
Requires-Dist: passlib (>=1.7,<2.0)
Requires-Dist: psycopg2-binary (>=2.8,<3.0)
Requires-Dist: pyjwt (>=1.7,<2.0)
Requires-Dist: pytest (>=5.2,<6.0)
Requires-Dist: pytest-asyncio (>=0.10.0,<0.11.0)
Requires-Dist: python-multipart (>=0.0.5,<0.0.6)
Requires-Dist: pyyaml (>=5.1,<6.0)
Requires-Dist: pyzmq (>=18.1,<19.0)
Requires-Dist: starlette (>=0.12.10,<0.13.0)
Requires-Dist: uvicorn (>=0.9.0,<0.10.0)
